uv_testing_pycon_italy_2025/__init__.py
uv_testing_pycon_italy_2025-0.1.2.dist-info/METADATA
uv_testing_pycon_italy_2025-0.1.2.dist-info/WHEEL
uv_testing_pycon_italy_2025-0.1.2.dist-info/entry_points.txt
uv_testing_pycon_italy_2025-0.1.2.dist-info/RECORD
